[{"Process Order":"53023","0":"53023","STOCKDATE":"2024-02-26 00:00:00.000","1":"2024-02-26 00:00:00.000","Item Name":"SITE FIXINGS PACK FOR SO 171194","2":"SITE FIXINGS PACK FOR SO 171194"},{"Process Order":"53024","0":"53024","STOCKDATE":"2024-02-26 00:00:00.000","1":"2024-02-26 00:00:00.000","Item Name":"WELDING FIXTURE WF GRAVITY LEG - KS345989","2":"WELDING FIXTURE WF GRAVITY LEG - KS345989"},{"Process Order":"52669","0":"52669","STOCKDATE":"2024-02-26 00:00:00.000","1":"2024-02-26 00:00:00.000","Item Name":"KSP - Type: Security Lock-down & Sealed\/ Clear Ope: 500x500 mm\/ Tray Depth: 75 mm\/ Loading: C250\/ Grade: 316 S\/S - KS323788","2":"KSP - Type: Security Lock-down & Sealed\/ Clear Ope: 500x500 mm\/ Tray Depth: 75 mm\/ Loading: C250\/ Grade: 316 S\/S - KS323788"},{"Process Order":"52666","0":"52666","STOCKDATE":"2024-02-26 00:00:00.000","1":"2024-02-26 00:00:00.000","Item Name":"KSP - Type: Security Lock-down & Sealed\/ Clear Ope: 300x300 mm\/ Tray Depth: 50 mm\/ Loading: C250\/ Grade: 316 S\/S - KS265980","2":"KSP - Type: Security Lock-down & Sealed\/ Clear Ope: 300x300 mm\/ Tray Depth: 50 mm\/ Loading: C250\/ Grade: 316 S\/S - KS265980"},{"Process Order":"53174","0":"53174","STOCKDATE":"2024-02-26 00:00:00.000","1":"2024-02-26 00:00:00.000","Item Name":"SITE FIXING PACK - 171253","2":"SITE FIXING PACK - 171253"},{"Process Order":"52975","0":"52975","STOCKDATE":"2024-02-26 00:00:00.000","1":"2024-02-26 00:00:00.000","Item Name":"GM - Beam\/Plates\/Fixings","2":"GM - Beam\/Plates\/Fixings"},{"Process Order":"53074","0":"53074","STOCKDATE":"2024-02-26 00:00:00.000","1":"2024-02-26 00:00:00.000","Item Name":"KMG150304 146x700 22\/22 25x2 304S\/S OFF-STD Polished Mesh","2":"KMG150304 146x700 22\/22 25x2 304S\/S OFF-STD Polished Mesh"},{"Process Order":"52853","0":"52853","STOCKDATE":"2024-02-26 00:00:00.000","1":"2024-02-26 00:00:00.000","Item Name":"Space House: KDWHMG 125 - to suit M100 ACO - Standard Length of 996 mm - Steel Grade: 316","2":"Space House: KDWHMG 125 - to suit M100 ACO - Standard Length of 996 mm - Steel Grade: 316"},{"Process Order":"52848","0":"52848","STOCKDATE":"2024-02-26 00:00:00.000","1":"2024-02-26 00:00:00.000","Item Name":"Space House: Channel & Grating - Width: 300 mm\/ Depth: 75 mm\/ Steel Grade: 316 - Meters of","2":"Space House: Channel & Grating - Width: 300 mm\/ Depth: 75 mm\/ Steel Grade: 316 - Meters of"},{"Process Order":"53101","0":"53101","STOCKDATE":"2024-02-26 00:00:00.000","1":"2024-02-26 00:00:00.000","Item Name":"1 no Channels Required For Roller Doors 19\/02\/24 KSBC150 Kents","2":"1 no Channels Required For Roller Doors 19\/02\/24 KSBC150 Kents"},{"Process Order":"52854","0":"52854","STOCKDATE":"2024-02-26 00:00:00.000","1":"2024-02-26 00:00:00.000","Item Name":"Space House: KDWHMG 125 - to suit M100 ACO - Bespoke Sections (4 No. Sections) - Steel Grade: 316 - Meters Of","2":"Space House: KDWHMG 125 - to suit M100 ACO - Bespoke Sections (4 No. Sections) - Steel Grade: 316 - Meters Of"}]